{
  "sampleKind": "real-groth16-invalid-tally-proof-v2",
  "generatedBy": "pnpm zk:samples",
  "expectedValid": false,
  "invalidReason": "tally vector [3,1,2,2] does not match the 8x4 witness column sums [2,2,2,2]",
  "request": {
    "electionId": "election_fixture_8x4",
    "voteVectors": [
      [
        1,
        0,
        0,
        0
      ],
      [
        0,
        1,
        0,
        0
      ],
      [
        0,
        0,
        1,
        0
      ],
      [
        0,
        0,
        0,
        1
      ],
      [
        1,
        0,
        0,
        0
      ],
      [
        0,
        1,
        0,
        0
      ],
      [
        0,
        0,
        1,
        0
      ],
      [
        0,
        0,
        0,
        1
      ]
    ],
    "realRows": [
      1,
      1,
      1,
      1,
      1,
      1,
      1,
      1
    ],
    "tally": [
      3,
      1,
      2,
      2
    ]
  },
  "proofId": "zkp_tally_c7c3dd1f-9e03-41b6-a664-b393b59373c9",
  "proofMode": "real",
  "verifierMode": "real-hardhat",
  "circuitId": "tally-correctness-8x4",
  "publicSignals": {
    "electionIdHash": "86ea05499d22abc3fe96a390140f373fc30e911ba0531feac69bba0037d179b9",
    "batchId": "fixture-8x4-invalid-tally",
    "tally": [
      3,
      1,
      2,
      2
    ],
    "batchSize": 8,
    "validVoteCount": 8,
    "candidateCount": 4,
    "tallyHash": "ede2c70cc1f5e1251c51a00eee5d3b4f0070ae28a13e0ff6fd88c6194cbdb55a",
    "commitmentRoot": "7d52dd9b91bbcfddb6d5a1520d27c93f011c32ef45dc0120d0df8794cf87d68a",
    "partitionHash": "1dc8d841928022d3f49a00b7bb2cf8799db460040eff9fbc525762aff2d4e959",
    "circuitId": "tally-correctness-8x4"
  },
  "proof": {
    "protocol": "verivote-tally-correctness-groth16-v1",
    "proofMode": "real",
    "verifierMode": "real-hardhat",
    "proofId": "zkp_tally_c7c3dd1f-9e03-41b6-a664-b393b59373c9",
    "circuitId": "tally-correctness-8x4",
    "generatedAt": "2026-06-27T09:30:46.669Z",
    "electionIdHash": "86ea05499d22abc3fe96a390140f373fc30e911ba0531feac69bba0037d179b9",
    "publicSignals": {
      "electionIdHash": "86ea05499d22abc3fe96a390140f373fc30e911ba0531feac69bba0037d179b9",
      "batchId": "fixture-8x4-invalid-tally",
      "tally": [
        3,
        1,
        2,
        2
      ],
      "batchSize": 8,
      "validVoteCount": 8,
      "candidateCount": 4,
      "tallyHash": "ede2c70cc1f5e1251c51a00eee5d3b4f0070ae28a13e0ff6fd88c6194cbdb55a",
      "commitmentRoot": "7d52dd9b91bbcfddb6d5a1520d27c93f011c32ef45dc0120d0df8794cf87d68a",
      "partitionHash": "1dc8d841928022d3f49a00b7bb2cf8799db460040eff9fbc525762aff2d4e959",
      "circuitId": "tally-correctness-8x4"
    },
    "snarkjsProof": null,
    "snarkjsPublicSignals": [],
    "artifactDirectory": "E:\\666\\-2-main\\zk-artifacts\\tally-correctness",
    "valid": false,
    "error": "tally[0] (3) does not match column sum (2)",
    "proofHash": "3a2f38a4b3adaadc35688e6bd4e32a2462767d5072466c7336ad129fbc584c63"
  },
  "proofHash": "3a2f38a4b3adaadc35688e6bd4e32a2462767d5072466c7336ad129fbc584c63",
  "valid": false,
  "message": "tally[0] (3) does not match column sum (2)"
}
